opm_unshear/__init__.py
opm_unshear/__main__.py
opm_unshear/cpu.py
opm_unshear/gpu.py
opm_unshear-0.0.1.dist-info/licenses/LICENSE
opm_unshear-0.0.1.dist-info/METADATA
opm_unshear-0.0.1.dist-info/WHEEL
opm_unshear-0.0.1.dist-info/top_level.txt
opm_unshear-0.0.1.dist-info/RECORD
