Metadata-Version: 2.4
Name: opm_unshear
Version: 0.0.1
Summary: opm_unshear for Python
Author: jlab.berlin, Maximilian Hoffmann, Benjamin Judkewitz
License: MIT
Project-URL: Homepage, https://github.com/danionella/opm_unshear
Keywords: opm_unshear,python
Requires-Python: >=3.9
License-File: LICENSE
Requires-Dist: numpy
Requires-Dist: tqdm
Requires-Dist: cupy
Requires-Dist: h5py
Requires-Dist: hdf5plugin
Requires-Dist: tifffile
Requires-Dist: scipy
Requires-Dist: numba
Dynamic: license-file
